test_package/__init__.py
test_package_jluna-0.1.0.dist-info/METADATA
test_package_jluna-0.1.0.dist-info/WHEEL
test_package_jluna-0.1.0.dist-info/top_level.txt
test_package_jluna-0.1.0.dist-info/RECORD
