Metadata-Version: 2.4
Name: test-package-jluna
Version: 0.1.0
Summary: A test Python package for upload testing
Author: Johan Luna
Author-email: johan.luna@finkargo.com
Classifier: Programming Language :: Python :: 3
Classifier: License :: OSI Approved :: MIT License
Classifier: Operating System :: OS Independent
Requires-Python: >=3.7
Dynamic: author
Dynamic: author-email
Dynamic: classifier
Dynamic: description
Dynamic: description-content-type
Dynamic: requires-python
Dynamic: summary
